hyperelastic/__about__.py
hyperelastic/__init__.py
hyperelastic/frameworks/__init__.py
hyperelastic/frameworks/_generalized.py
hyperelastic/frameworks/_invariants.py
hyperelastic/frameworks/_stretches.py
hyperelastic/lab/__init__.py
hyperelastic/lab/_curve_fit.py
hyperelastic/lab/_experiment.py
hyperelastic/lab/_load_case.py
hyperelastic/lab/_optimize.py
hyperelastic/lab/_plotting.py
hyperelastic/lab/_simulation.py
hyperelastic/math/__init__.py
hyperelastic/math/_voigt.py
hyperelastic/models/__init__.py
hyperelastic/models/generalized/__init__.py
hyperelastic/models/generalized/_stretch.py
hyperelastic/models/invariants/__init__.py
hyperelastic/models/invariants/_third_order_deformation.py
hyperelastic/models/invariants/_torch.py
hyperelastic/models/stretches/__init__.py
hyperelastic/models/stretches/_generalized_invariants.py
hyperelastic/models/stretches/_ogden.py
hyperelastic/spaces/__init__.py
hyperelastic/spaces/_deformation.py
hyperelastic/spaces/_dilatational.py
hyperelastic/spaces/_distortional.py
hyperelastic/spaces/_space.py
hyperelastic-0.10.2.dist-info/LICENSE
hyperelastic-0.10.2.dist-info/METADATA
hyperelastic-0.10.2.dist-info/WHEEL
hyperelastic-0.10.2.dist-info/top_level.txt
hyperelastic-0.10.2.dist-info/RECORD
