Metadata-Version: 2.2
Name: hyperelastic
Version: 0.10.2
Summary: Constitutive hyperelastic material formulations for FElupe
Author-email: Andreas Dutzler <a.dutzler@gmail.com>
License:                     GNU GENERAL PUBLIC LICENSE
Project-URL: Homepage, https://github.com/adtzlr/hyperelastic
Project-URL: Code, https://github.com/adtzlr/hyperelastic
Project-URL: Issues, https://github.com/adtzlr/hyperelastic/issues
Keywords: python,constitution,scientific-computing,fem,finite-elements-analysis,hyperelasticity
Classifier: Development Status :: 5 - Production/Stable
Classifier: Programming Language :: Python
Classifier: Intended Audience :: Science/Research
Classifier: License :: OSI Approved :: GNU General Public License v3 or later (GPLv3+)
Classifier: Operating System :: OS Independent
Classifier: Programming Language :: Python
Classifier: Programming Language :: Python :: 3
Classifier: Programming Language :: Python :: 3.9
Classifier: Programming Language :: Python :: 3.10
Classifier: Programming Language :: Python :: 3.11
Classifier: Programming Language :: Python :: 3.12
Classifier: Programming Language :: Python :: 3.13
Classifier: Topic :: Scientific/Engineering
Classifier: Topic :: Scientific/Engineering :: Mathematics
Classifier: Topic :: Utilities
Requires-Python: >=3.9
License-File: LICENSE
Requires-Dist: numpy
Requires-Dist: scipy
Requires-Dist: matplotlib
Provides-Extra: docs
Requires-Dist: pydata-sphinx-theme; extra == "docs"
Requires-Dist: sphinx-copybutton; extra == "docs"
Requires-Dist: myst-nb; extra == "docs"
Provides-Extra: test
Requires-Dist: felupe; extra == "test"
Requires-Dist: sympy; extra == "test"
Requires-Dist: torch; extra == "test"
Requires-Dist: einsumt; extra == "test"
